apppy/logger/__init__.py
apppy/logger/filter.py
apppy/logger/format.py
apppy/logger/format_unit_test.py
apppy/logger/parser.py
apppy/logger/storage.py
apppy_logger-0.23.2.dist-info/METADATA
apppy_logger-0.23.2.dist-info/WHEEL
apppy_logger-0.23.2.dist-info/RECORD
