Metadata-Version: 2.4
Name: apppy-logger
Version: 0.23.2
Summary: Python logger extensions for server development
Project-URL: Homepage, https://github.com/spals/apppy
Author: Tim Kral
License: MIT
Classifier: License :: OSI Approved :: MIT License
Classifier: Programming Language :: Python :: 3
Requires-Python: >=3.11
